py_ltl_parser/__init__.py
py_ltl_parser/ltl_semantics/__init__.py
py_ltl_parser/ltl_semantics/lexer.py
py_ltl_parser/ltl_semantics/ltl.py
py_ltl_parser/ltl_semantics/parser.py
py_ltl_parser/ltl_semantics/parsetab.py
py_ltl_parser/parsers/__init__.py
py_ltl_parser/parsers/parsetab.py
py_ltl_parser/parsers/upaal_ltl_parser.py
py_ltl_parser/parsers/xstampp_parser.py
py_ltl_parser-0.1.0a0.dist-info/METADATA
py_ltl_parser-0.1.0a0.dist-info/WHEEL
py_ltl_parser-0.1.0a0.dist-info/top_level.txt
py_ltl_parser-0.1.0a0.dist-info/RECORD
